fastsqla.py
fastsqla-0.5.1.dist-info/METADATA
fastsqla-0.5.1.dist-info/WHEEL
fastsqla-0.5.1.dist-info/top_level.txt
fastsqla-0.5.1.dist-info/RECORD
