Metadata-Version: 2.4
Name: FastSQLA
Version: 0.5.1
Summary: SQLAlchemy extension for FastAPI that supports asynchronous sessions and includes built-in pagination.
Author-email: Hadrien David <h@driendavid.com>
Project-URL: Homepage, https://github.com/hadrien/fastsqla
Project-URL: Documentation, https://github.com/hadrien/fastsqla
Project-URL: Repository, https://github.com/hadrien/fastsqla
Project-URL: Issues, https://github.com/hadrien/fastsqla/issues
Project-URL: Changelog, https://github.com/hadrien/fastsqla/releases
Keywords: FastAPI,SQLAlchemy,AsyncIO
Classifier: Development Status :: 4 - Beta
Classifier: Environment :: Web Environment
Classifier: Framework :: AsyncIO
Classifier: Framework :: FastAPI
Classifier: Framework :: Pydantic :: 2
Classifier: Framework :: Pydantic
Classifier: Intended Audience :: Developers
Classifier: Intended Audience :: Information Technology
Classifier: Intended Audience :: System Administrators
Classifier: Operating System :: OS Independent
Classifier: Programming Language :: Python :: 3 :: Only
Classifier: Programming Language :: Python :: 3.12
Classifier: Programming Language :: Python :: 3
Classifier: Programming Language :: Python
Classifier: Programming Language :: SQL
Classifier: Topic :: Internet :: WWW/HTTP :: HTTP Servers
Classifier: Topic :: Internet :: WWW/HTTP
Classifier: Topic :: Internet
Classifier: Topic :: Software Development :: Libraries :: Application Frameworks
Classifier: Topic :: Software Development :: Libraries :: Python Modules
Classifier: Topic :: Software Development :: Libraries
Classifier: Topic :: Software Development
Classifier: Typing :: Typed
Requires-Python: >=3.12
Requires-Dist: fastapi>=0.115.6
Requires-Dist: sqlalchemy[asyncio]>=2.0.37
Requires-Dist: structlog>=24.4.0
Provides-Extra: docs
Requires-Dist: mkdocs-glightbox>=0.5.2; extra == "docs"
Requires-Dist: mkdocs-llmstxt>=0.5.0; extra == "docs"
Requires-Dist: mkdocs-material>=9.7.1; extra == "docs"
Requires-Dist: mkdocstrings[python]>=1.0.0; extra == "docs"
Provides-Extra: sqlmodel
Requires-Dist: sqlmodel>=0.0.22; extra == "sqlmodel"
